Workbook
Name ListaClientes: Clientes!$A$4:$A$203
Name ListaEmprestimos: Empréstimos!$A$4:$A$203

Sheet Clientes
A1: Cadastro de Clientes
A2: Insira um cliente por linha. Campos em azul são editáveis; use IDs únicos como CLI-0001.
A3: ID Cliente | B3: Nome completo | C3: CPF/CNPJ | D3: Nascimento/Abertura | E3: Telefone | F3: E-mail | G3: Endereço | H3: Status | I3: Data de cadastro | J3: Validação
A4: CLI-0001 | B4: Cliente Teste | C4: 000.000.000-00 | E4: (00) 00000-0000 | F4: cliente@teste.com | G4: Endereço de teste | H4: Ativo | I4: 46236.167 | J4: =IF(A4="","",IF(COUNTIF($A$4:$A$203,A4)>1,"ID duplicado",IF(AND(C4<>"",COUNTIF($C$4:$C$203,C4)>1),"CPF/CNPJ duplicado","OK"))) -> OK
A5: CLI-0002 | B5: Teste 1 | H5: Ativo | I5: 46236.167 | J5: =IF(A5="","",IF(COUNTIF($A$4:$A$203,A5)>1,"ID duplicado",IF(AND(C5<>"",COUNTIF($C$4:$C$203,C5)>1),"CPF/CNPJ duplicado","OK"))) -> OK
J6: =IF(A6="","",IF(COUNTIF($A$4:$A$203,A6)>1,"ID duplicado",IF(AND(C6<>"",COUNTIF($C$4:$C$203,C6)>1),"CPF/CNPJ duplicado","OK")))
J7: =IF(A7="","",IF(COUNTIF($A$4:$A$203,A7)>1,"ID duplicado",IF(AND(C7<>"",COUNTIF($C$4:$C$203,C7)>1),"CPF/CNPJ duplicado","OK")))
J8: =IF(A8="","",IF(COUNTIF($A$4:$A$203,A8)>1,"ID duplicado",IF(AND(C8<>"",COUNTIF($C$4:$C$203,C8)>1),"CPF/CNPJ duplicado","OK")))
J9: =IF(A9="","",IF(COUNTIF($A$4:$A$203,A9)>1,"ID duplicado",IF(AND(C9<>"",COUNTIF($C$4:$C$203,C9)>1),"CPF/CNPJ duplicado","OK")))
J10: =IF(A10="","",IF(COUNTIF($A$4:$A$203,A10)>1,"ID duplicado",IF(AND(C10<>"",COUNTIF($C$4:$C$203,C10)>1),"CPF/CNPJ duplicado","OK")))
J11: =IF(A11="","",IF(COUNTIF($A$4:$A$203,A11)>1,"ID duplicado",IF(AND(C11<>"",COUNTIF($C$4:$C$203,C11)>1),"CPF/CNPJ duplicado","OK")))
J12: =IF(A12="","",IF(COUNTIF($A$4:$A$203,A12)>1,"ID duplicado",IF(AND(C12<>"",COUNTIF($C$4:$C$203,C12)>1),"CPF/CNPJ duplicado","OK")))
J13: =IF(A13="","",IF(COUNTIF($A$4:$A$203,A13)>1,"ID duplicado",IF(AND(C13<>"",COUNTIF($C$4:$C$203,C13)>1),"CPF/CNPJ duplicado","OK")))
J14: =IF(A14="","",IF(COUNTIF($A$4:$A$203,A14)>1,"ID duplicado",IF(AND(C14<>"",COUNTIF($C$4:$C$203,C14)>1),"CPF/CNPJ duplicado","OK")))
J15: =IF(A15="","",IF(COUNTIF($A$4:$A$203,A15)>1,"ID duplicado",IF(AND(C15<>"",COUNTIF($C$4:$C$203,C15)>1),"CPF/CNPJ duplicado","OK")))
J16: =IF(A16="","",IF(COUNTIF($A$4:$A$203,A16)>1,"ID duplicado",IF(AND(C16<>"",COUNTIF($C$4:$C$203,C16)>1),"CPF/CNPJ duplicado","OK")))
J17: =IF(A17="","",IF(COUNTIF($A$4:$A$203,A17)>1,"ID duplicado",IF(AND(C17<>"",COUNTIF($C$4:$C$203,C17)>1),"CPF/CNPJ duplicado","OK")))
... J203: =IF(A203="","",IF(COUNTIF($A$4:$A$203,A203)>1,"ID duplicado",IF(AND(C203<>"",COUNTIF($C$4:$C$203,C203)>1),"CPF/CNPJ duplicado","OK")))

Sheet Empréstimos
A1: Empréstimos por Cliente
A2: Cadastre o contrato, selecione um ID de cliente existente e acompanhe os valores calculados.
A3: ID Empréstimo | B3: ID Cliente | C3: Nome do cliente | D3: Data contratação | E3: Valor principal | F3: Taxa anual efetiva | G3: Prazo (meses) | H3: Tarifas iniciais | I3: Seguro mensal | J3: Taxa mensal | K3: Parcela financeira | L3: Pagamento mensal | M3: Total previsto | N3: Juros previstos | O3: Status | P3: Observações | Q3: Validação
A4: EMP-0001 | B4: CLI-0001 | C4: =IF(B4="","",IFERROR(INDEX(Clientes!$B$4:$B$203,MATCH(B4,Clientes!$A$4:$A$203,0)),"Cliente não encontrado")) -> Cliente Teste | D4: 46236.167 | E4: 100000 | F4: 0.12 | G4: 24 | H4: 0 | I4: 0 | J4: =IF(OR(E4="",F4="",G4=""),"",(1+F4)^(1/12)-1) -> 0.0094887929 | K4: =IF(OR(E4<=0,G4<=0),"",-PMT(J4,G4,E4)) -> 4678.7507 | L4: =IF(K4="","",K4+I4) -> 4678.7507 | M4: =IF(L4="","",L4*G4+H4) -> 112290.02 | N4: =IF(K4="","",K4*G4-E4) -> 12290.018 | O4: Ativo | P4: Empréstimo de teste migrado da versão anterior. | Q4: =IF(A4="","",IF(COUNTIF($A$4:$A$203,A4)>1,"ID duplicado",IF(COUNTIF(Clientes!$A$4:$A$203,B4)=0,"Cliente não encontrado",IF(OR(E4<=0,G4<=0,F4<0),"Revisar condições","OK")))) -> OK
A5: EMP-0002 | B5: CLI-0002 | C5: =IF(B5="","",IFERROR(INDEX(Clientes!$B$4:$B$203,MATCH(B5,Clientes!$A$4:$A$203,0)),"Cliente não encontrado")) -> Teste 1 | D5: 46236.167 | E5: 1000 | F5: 7.9161004 | G5: 10 | H5: 0 | I5: 0 | J5: =IF(OR(E5="",F5="",G5=""),"",(1+F5)^(1/12)-1) -> 0.2 | K5: =IF(OR(E5<=0,G5<=0),"",-PMT(J5,G5,E5)) -> 238.52276 | L5: =IF(K5="","",K5+I5) -> 238.52276 | M5: =IF(L5="","",L5*G5+H5) -> 2385.2276 | N5: =IF(K5="","",K5*G5-E5) -> 1385.2276 | O5: Ativo | P5: CLI-0002 — taxa informada: 20% a.m.; equivalente anual armazenado. | Q5: =IF(A5="","",IF(COUNTIF($A$4:$A$203,A5)>1,"ID duplicado",IF(COUNTIF(Clientes!$A$4:$A$203,B5)=0,"Cliente não encontrado",IF(OR(E5<=0,G5<=0,F5<0),"Revisar condições","OK")))) -> OK
C6: =IF(B6="","",IFERROR(INDEX(Clientes!$B$4:$B$203,MATCH(B6,Clientes!$A$4:$A$203,0)),"Cliente não encontrado")) | J6: =IF(OR(E6="",F6="",G6=""),"",(1+F6)^(1/12)-1) | K6: =IF(OR(E6<=0,G6<=0),"",-PMT(J6,G6,E6)) | L6: =IF(K6="","",K6+I6) | M6: =IF(L6="","",L6*G6+H6) | N6: =IF(K6="","",K6*G6-E6) | Q6: =IF(A6="","",IF(COUNTIF($A$4:$A$203,A6)>1,"ID duplicado",IF(COUNTIF(Clientes!$A$4:$A$203,B6)=0,"Cliente não encontrado",IF(OR(E6<=0,G6<=0,F6<0),"Revisar condições","OK"))))
C7: =IF(B7="","",IFERROR(INDEX(Clientes!$B$4:$B$203,MATCH(B7,Clientes!$A$4:$A$203,0)),"Cliente não encontrado")) | J7: =IF(OR(E7="",F7="",G7=""),"",(1+F7)^(1/12)-1) | K7: =IF(OR(E7<=0,G7<=0),"",-PMT(J7,G7,E7)) | L7: =IF(K7="","",K7+I7) | M7: =IF(L7="","",L7*G7+H7) | N7: =IF(K7="","",K7*G7-E7) | Q7: =IF(A7="","",IF(COUNTIF($A$4:$A$203,A7)>1,"ID duplicado",IF(COUNTIF(Clientes!$A$4:$A$203,B7)=0,"Cliente não encontrado",IF(OR(E7<=0,G7<=0,F7<0),"Revisar condições","OK"))))
C8: =IF(B8="","",IFERROR(INDEX(Clientes!$B$4:$B$203,MATCH(B8,Clientes!$A$4:$A$203,0)),"Cliente não encontrado")) | J8: =IF(OR(E8="",F8="",G8=""),"",(1+F8)^(1/12)-1) | K8: =IF(OR(E8<=0,G8<=0),"",-PMT(J8,G8,E8)) | L8: =IF(K8="","",K8+I8) | M8: =IF(L8="","",L8*G8+H8) | N8: =IF(K8="","",K8*G8-E8) | Q8: =IF(A8="","",IF(COUNTIF($A$4:$A$203,A8)>1,"ID duplicado",IF(COUNTIF(Clientes!$A$4:$A$203,B8)=0,"Cliente não encontrado",IF(OR(E8<=0,G8<=0,F8<0),"Revisar condições","OK"))))
C9: =IF(B9="","",IFERROR(INDEX(Clientes!$B$4:$B$203,MATCH(B9,Clientes!$A$4:$A$203,0)),"Cliente não encontrado")) | J9: =IF(OR(E9="",F9="",G9=""),"",(1+F9)^(1/12)-1) | K9: =IF(OR(E9<=0,G9<=0),"",-PMT(J9,G9,E9)) | L9: =IF(K9="","",K9+I9) | M9: =IF(L9="","",L9*G9+H9) | N9: =IF(K9="","",K9*G9-E9) | Q9: =IF(A9="","",IF(COUNTIF($A$4:$A$203,A9)>1,"ID duplicado",IF(COUNTIF(Clientes!$A$4:$A$203,B9)=0,"Cliente não encontrado",IF(OR(E9<=0,G9<=0,F9<0),"Revisar condições","OK"))))
C10: =IF(B10="","",IFERROR(INDEX(Clientes!$B$4:$B$203,MATCH(B10,Clientes!$A$4:$A$203,0)),"Cliente não encontrado")) | J10: =IF(OR(E10="",F10="",G10=""),"",(1+F10)^(1/12)-1) | K10: =IF(OR(E10<=0,G10<=0),"",-PMT(J10,G10,E10)) | L10: =IF(K10="","",K10+I10) | M10: =IF(L10="","",L10*G10+H10) | N10: =IF(K10="","",K10*G10-E10) | Q10: =IF(A10="","",IF(COUNTIF($A$4:$A$203,A10)>1,"ID duplicado",IF(COUNTIF(Clientes!$A$4:$A$203,B10)=0,"Cliente não encontrado",IF(OR(E10<=0,G10<=0,F10<0),"Revisar condições","OK"))))
C11: =IF(B11="","",IFERROR(INDEX(Clientes!$B$4:$B$203,MATCH(B11,Clientes!$A$4:$A$203,0)),"Cliente não encontrado")) | J11: =IF(OR(E11="",F11="",G11=""),"",(1+F11)^(1/12)-1) | K11: =IF(OR(E11<=0,G11<=0),"",-PMT(J11,G11,E11)) | L11: =IF(K11="","",K11+I11) | M11: =IF(L11="","",L11*G11+H11) | N11: =IF(K11="","",K11*G11-E11) | Q11: =IF(A11="","",IF(COUNTIF($A$4:$A$203,A11)>1,"ID duplicado",IF(COUNTIF(Clientes!$A$4:$A$203,B11)=0,"Cliente não encontrado",IF(OR(E11<=0,G11<=0,F11<0),"Revisar condições","OK"))))
C12: =IF(B12="","",IFERROR(INDEX(Clientes!$B$4:$B$203,MATCH(B12,Clientes!$A$4:$A$203,0)),"Cliente não encontrado")) | J12: =IF(OR(E12="",F12="",G12=""),"",(1+F12)^(1/12)-1) | K12: =IF(OR(E12<=0,G12<=0),"",-PMT(J12,G12,E12)) | L12: =IF(K12="","",K12+I12) | M12: =IF(L12="","",L12*G12+H12) | N12: =IF(K12="","",K12*G12-E12) | Q12: =IF(A12="","",IF(COUNTIF($A$4:$A$203,A12)>1,"ID duplicado",IF(COUNTIF(Clientes!$A$4:$A$203,B12)=0,"Cliente não encontrado",IF(OR(E12<=0,G12<=0,F12<0),"Revisar condições","OK"))))
C13: =IF(B13="","",IFERROR(INDEX(Clientes!$B$4:$B$203,MATCH(B13,Clientes!$A$4:$A$203,0)),"Cliente não encontrado")) | J13: =IF(OR(E13="",F13="",G13=""),"",(1+F13)^(1/12)-1) | K13: =IF(OR(E13<=0,G13<=0),"",-PMT(J13,G13,E13)) | L13: =IF(K13="","",K13+I13) | M13: =IF(L13="","",L13*G13+H13) | N13: =IF(K13="","",K13*G13-E13) | Q13: =IF(A13="","",IF(COUNTIF($A$4:$A$203,A13)>1,"ID duplicado",IF(COUNTIF(Clientes!$A$4:$A$203,B13)=0,"Cliente não encontrado",IF(OR(E13<=0,G13<=0,F13<0),"Revisar condições","OK"))))
C14: =IF(B14="","",IFERROR(INDEX(Clientes!$B$4:$B$203,MATCH(B14,Clientes!$A$4:$A$203,0)),"Cliente não encontrado")) | J14: =IF(OR(E14="",F14="",G14=""),"",(1+F14)^(1/12)-1) | K14: =IF(OR(E14<=0,G14<=0),"",-PMT(J14,G14,E14)) | L14: =IF(K14="","",K14+I14) | M14: =IF(L14="","",L14*G14+H14) | N14: =IF(K14="","",K14*G14-E14) | Q14: =IF(A14="","",IF(COUNTIF($A$4:$A$203,A14)>1,"ID duplicado",IF(COUNTIF(Clientes!$A$4:$A$203,B14)=0,"Cliente não encontrado",IF(OR(E14<=0,G14<=0,F14<0),"Revisar condições","OK"))))
C15: =IF(B15="","",IFERROR(INDEX(Clientes!$B$4:$B$203,MATCH(B15,Clientes!$A$4:$A$203,0)),"Cliente não encontrado")) | J15: =IF(OR(E15="",F15="",G15=""),"",(1+F15)^(1/12)-1) | K15: =IF(OR(E15<=0,G15<=0),"",-PMT(J15,G15,E15)) | L15: =IF(K15="","",K15+I15) | M15: =IF(L15="","",L15*G15+H15) | N15: =IF(K15="","",K15*G15-E15) | Q15: =IF(A15="","",IF(COUNTIF($A$4:$A$203,A15)>1,"ID duplicado",IF(COUNTIF(Clientes!$A$4:$A$203,B15)=0,"Cliente não encontrado",IF(OR(E15<=0,G15<=0,F15<0),"Revisar condições","OK"))))
C16: =IF(B16="","",IFERROR(INDEX(Clientes!$B$4:$B$203,MATCH(B16,Clientes!$A$4:$A$203,0)),"Cliente não encontrado")) | J16: =IF(OR(E16="",F16="",G16=""),"",(1+F16)^(1/12)-1) | K16: =IF(OR(E16<=0,G16<=0),"",-PMT(J16,G16,E16)) | L16: =IF(K16="","",K16+I16) | M16: =IF(L16="","",L16*G16+H16) | N16: =IF(K16="","",K16*G16-E16) | Q16: =IF(A16="","",IF(COUNTIF($A$4:$A$203,A16)>1,"ID duplicado",IF(COUNTIF(Clientes!$A$4:$A$203,B16)=0,"Cliente não encontrado",IF(OR(E16<=0,G16<=0,F16<0),"Revisar condições","OK"))))
C17: =IF(B17="","",IFERROR(INDEX(Clientes!$B$4:$B$203,MATCH(B17,Clientes!$A$4:$A$203,0)),"Cliente não encontrado")) | J17: =IF(OR(E17="",F17="",G17=""),"",(1+F17)^(1/12)-1) | K17: =IF(OR(E17<=0,G17<=0),"",-PMT(J17,G17,E17)) | L17: =IF(K17="","",K17+I17) | M17: =IF(L17="","",L17*G17+H17) | N17: =IF(K17="","",K17*G17-E17) | Q17: =IF(A17="","",IF(COUNTIF($A$4:$A$203,A17)>1,"ID duplicado",IF(COUNTIF(Clientes!$A$4:$A$203,B17)=0,"Cliente não encontrado",IF(OR(E17<=0,G17<=0,F17<0),"Revisar condições","OK"))))
... C203: =IF(B203="","",IFERROR(INDEX(Clientes!$B$4:$B$203,MATCH(B203,Clientes!$A$4:$A$203,0)),"Cliente não encontrado")) | J203: =IF(OR(E203="",F203="",G203=""),"",(1+F203)^(1/12)-1) | K203: =IF(OR(E203<=0,G203<=0),"",-PMT(J203,G203,E203)) | L203: =IF(K203="","",K203+I203) | M203: =IF(L203="","",L203*G203+H203) | N203: =IF(K203="","",K203*G203-E203) | Q203: =IF(A203="","",IF(COUNTIF($A$4:$A$203,A203)>1,"ID duplicado",IF(COUNTIF(Clientes!$A$4:$A$203,B203)=0,"Cliente não encontrado",IF(OR(E203<=0,G203<=0,F203<0),"Revisar condições","OK"))))

Sheet Simulador
A1: Consulta de Empréstimo — Tabela Price
A2: Informe o ID de um contrato cadastrado para consultar cliente, condições e cronograma.
A3: ID do empréstimo | B3: EMP-0002 | E3: Como usar
E4: 1. Cadastre o cliente na aba Clientes. 2. Cadastre o contrato na aba Empréstimos usando o ID do cliente. 3. Informe o ID do contrato nesta aba para consultar o cronograma.
A5: Cliente vinculado
A6: ID Cliente | B6: =IFERROR(INDEX(Empréstimos!$B$4:$B$203,MATCH($B$3,Empréstimos!$A$4:$A$203,0)),"") -> CLI-0002
A7: Nome do cliente | B7: =IFERROR(INDEX(Empréstimos!$C$4:$C$203,MATCH($B$3,Empréstimos!$A$4:$A$203,0)),"") -> Teste 1
A9: Condições contratadas
A10: Data da contratação | B10: =IFERROR(INDEX(Empréstimos!$D$4:$D$203,MATCH($B$3,Empréstimos!$A$4:$A$203,0)),"") -> 46236.167 | E10: Legenda
A11: Valor principal | B11: =IFERROR(INDEX(Empréstimos!$E$4:$E$203,MATCH($B$3,Empréstimos!$A$4:$A$203,0)),"") -> 1000 | E11: Entrada editável | F11: Azul
A12: Taxa anual efetiva | B12: =IFERROR(INDEX(Empréstimos!$F$4:$F$203,MATCH($B$3,Empréstimos!$A$4:$A$203,0)),"") -> 7.9161004 | E12: Fórmula | F12: Preto
A13: Prazo (meses) | B13: =IFERROR(INDEX(Empréstimos!$G$4:$G$203,MATCH($B$3,Empréstimos!$A$4:$A$203,0)),"") -> 10 | E13: Referência entre abas | F13: Verde
A14: Tarifas iniciais | B14: =IFERROR(INDEX(Empréstimos!$H$4:$H$203,MATCH($B$3,Empréstimos!$A$4:$A$203,0)),"") -> 0
A15: Seguro mensal | B15: =IFERROR(INDEX(Empréstimos!$I$4:$I$203,MATCH($B$3,Empréstimos!$A$4:$A$203,0)),"") -> 0
A17: Resultados calculados
A18: Taxa mensal equivalente | B18: =IFERROR(INDEX(Empréstimos!$J$4:$J$203,MATCH($B$3,Empréstimos!$A$4:$A$203,0)),"") -> 0.2
A19: Parcela financeira | B19: =IFERROR(INDEX(Empréstimos!$K$4:$K$203,MATCH($B$3,Empréstimos!$A$4:$A$203,0)),"") -> 238.52276
A20: Pagamento mensal total | B20: =IFERROR(INDEX(Empréstimos!$L$4:$L$203,MATCH($B$3,Empréstimos!$A$4:$A$203,0)),"") -> 238.52276
A21: Total previsto | B21: =IFERROR(INDEX(Empréstimos!$M$4:$M$203,MATCH($B$3,Empréstimos!$A$4:$A$203,0)),"") -> 2385.2276
A22: Juros previstos | B22: =IFERROR(INDEX(Empréstimos!$N$4:$N$203,MATCH($B$3,Empréstimos!$A$4:$A$203,0)),"") -> 1385.2276
A23: CET anual aproximado | B23: =IFERROR((1+RATE(B13,-B20,B11-B14))^12-1,0) -> 7.9161004
A26: Verificações
A27: Empréstimo localizado | B27: =IF(B3="","Selecione",IF(COUNTIF(Empréstimos!$A$4:$A$203,B3)=1,"OK","REVISAR")) -> OK
A28: Cliente localizado | B28: =IF(B6="","REVISAR",IF(COUNTIF(Clientes!$A$4:$A$203,B6)=1,"OK","REVISAR")) -> OK
A29: Saldo final | B29: =IF(B13="","",INDEX(Amortização!F3:F362,B13)) -> 0
A30: Amortização acumulada | B30: =SUM(Amortização!E3:E362) -> 1000
A31: Diferença vs. principal | B31: =B30-B11 -> 0
A32: Status do modelo | B32: =IF(AND(B27="OK",B28="OK",ABS(B29)<0.01,ABS(B31)<0.01),"OK","REVISAR") -> OK

Sheet Amortização
A1: Cronograma do Empréstimo Selecionado
A2: Parcela | B2: Vencimento | C2: Saldo inicial | D2: Juros | E2: Amortização | F2: Saldo final | G2: Pagamento total
A3: =IF(ROW()-2<=Simulador!$B$13,ROW()-2,"") -> 1 | B3: =IF($A3="","",EDATE(Simulador!$B$10,$A3)) -> 46267 | C3: =IF($A3="","",IF($A3=1,Simulador!$B$11,$F2)) -> 1000 | D3: =IF($A3="","",$C3*Simulador!$B$18) -> 200 | E3: =IF($A3="","",MIN(Simulador!$B$19-$D3,$C3)) -> 38.522757 | F3: =IF($A3="","",MAX(0,$C3-$E3)) -> 961.47724 | G3: =IF($A3="","",$D3+$E3+Simulador!$B$15) -> 238.52276
A4: =IF(ROW()-2<=Simulador!$B$13,ROW()-2,"") -> 2 | B4: =IF($A4="","",EDATE(Simulador!$B$10,$A4)) -> 46297 | C4: =IF($A4="","",IF($A4=1,Simulador!$B$11,$F3)) -> 961.47724 | D4: =IF($A4="","",$C4*Simulador!$B$18) -> 192.29545 | E4: =IF($A4="","",MIN(Simulador!$B$19-$D4,$C4)) -> 46.227308 | F4: =IF($A4="","",MAX(0,$C4-$E4)) -> 915.24993 | G4: =IF($A4="","",$D4+$E4+Simulador!$B$15) -> 238.52276
A5: =IF(ROW()-2<=Simulador!$B$13,ROW()-2,"") -> 3 | B5: =IF($A5="","",EDATE(Simulador!$B$10,$A5)) -> 46328 | C5: =IF($A5="","",IF($A5=1,Simulador!$B$11,$F4)) -> 915.24993 | D5: =IF($A5="","",$C5*Simulador!$B$18) -> 183.04999 | E5: =IF($A5="","",MIN(Simulador!$B$19-$D5,$C5)) -> 55.47277 | F5: =IF($A5="","",MAX(0,$C5-$E5)) -> 859.77716 | G5: =IF($A5="","",$D5+$E5+Simulador!$B$15) -> 238.52276
A6: =IF(ROW()-2<=Simulador!$B$13,ROW()-2,"") -> 4 | B6: =IF($A6="","",EDATE(Simulador!$B$10,$A6)) -> 46358 | C6: =IF($A6="","",IF($A6=1,Simulador!$B$11,$F5)) -> 859.77716 | D6: =IF($A6="","",$C6*Simulador!$B$18) -> 171.95543 | E6: =IF($A6="","",MIN(Simulador!$B$19-$D6,$C6)) -> 66.567324 | F6: =IF($A6="","",MAX(0,$C6-$E6)) -> 793.20984 | G6: =IF($A6="","",$D6+$E6+Simulador!$B$15) -> 238.52276
A7: =IF(ROW()-2<=Simulador!$B$13,ROW()-2,"") -> 5 | B7: =IF($A7="","",EDATE(Simulador!$B$10,$A7)) -> 46389 | C7: =IF($A7="","",IF($A7=1,Simulador!$B$11,$F6)) -> 793.20984 | D7: =IF($A7="","",$C7*Simulador!$B$18) -> 158.64197 | E7: =IF($A7="","",MIN(Simulador!$B$19-$D7,$C7)) -> 79.880789 | F7: =IF($A7="","",MAX(0,$C7-$E7)) -> 713.32905 | G7: =IF($A7="","",$D7+$E7+Simulador!$B$15) -> 238.52276
A8: =IF(ROW()-2<=Simulador!$B$13,ROW()-2,"") -> 6 | B8: =IF($A8="","",EDATE(Simulador!$B$10,$A8)) -> 46420 | C8: =IF($A8="","",IF($A8=1,Simulador!$B$11,$F7)) -> 713.32905 | D8: =IF($A8="","",$C8*Simulador!$B$18) -> 142.66581 | E8: =IF($A8="","",MIN(Simulador!$B$19-$D8,$C8)) -> 95.856946 | F8: =IF($A8="","",MAX(0,$C8-$E8)) -> 617.47211 | G8: =IF($A8="","",$D8+$E8+Simulador!$B$15) -> 238.52276
A9: =IF(ROW()-2<=Simulador!$B$13,ROW()-2,"") -> 7 | B9: =IF($A9="","",EDATE(Simulador!$B$10,$A9)) -> 46448 | C9: =IF($A9="","",IF($A9=1,Simulador!$B$11,$F8)) -> 617.47211 | D9: =IF($A9="","",$C9*Simulador!$B$18) -> 123.49442 | E9: =IF($A9="","",MIN(Simulador!$B$19-$D9,$C9)) -> 115.02834 | F9: =IF($A9="","",MAX(0,$C9-$E9)) -> 502.44377 | G9: =IF($A9="","",$D9+$E9+Simulador!$B$15) -> 238.52276
A10: =IF(ROW()-2<=Simulador!$B$13,ROW()-2,"") -> 8 | B10: =IF($A10="","",EDATE(Simulador!$B$10,$A10)) -> 46479 | C10: =IF($A10="","",IF($A10=1,Simulador!$B$11,$F9)) -> 502.44377 | D10: =IF($A10="","",$C10*Simulador!$B$18) -> 100.48875 | E10: =IF($A10="","",MIN(Simulador!$B$19-$D10,$C10)) -> 138.034 | F10: =IF($A10="","",MAX(0,$C10-$E10)) -> 364.40977 | G10: =IF($A10="","",$D10+$E10+Simulador!$B$15) -> 238.52276
A11: =IF(ROW()-2<=Simulador!$B$13,ROW()-2,"") -> 9 | B11: =IF($A11="","",EDATE(Simulador!$B$10,$A11)) -> 46509 | C11: =IF($A11="","",IF($A11=1,Simulador!$B$11,$F10)) -> 364.40977 | D11: =IF($A11="","",$C11*Simulador!$B$18) -> 72.881953 | E11: =IF($A11="","",MIN(Simulador!$B$19-$D11,$C11)) -> 165.6408 | F11: =IF($A11="","",MAX(0,$C11-$E11)) -> 198.76896 | G11: =IF($A11="","",$D11+$E11+Simulador!$B$15) -> 238.52276
A12: =IF(ROW()-2<=Simulador!$B$13,ROW()-2,"") -> 10 | B12: =IF($A12="","",EDATE(Simulador!$B$10,$A12)) -> 46540 | C12: =IF($A12="","",IF($A12=1,Simulador!$B$11,$F11)) -> 198.76896 | D12: =IF($A12="","",$C12*Simulador!$B$18) -> 39.753793 | E12: =IF($A12="","",MIN(Simulador!$B$19-$D12,$C12)) -> 198.76896 | F12: =IF($A12="","",MAX(0,$C12-$E12)) -> 0 | G12: =IF($A12="","",$D12+$E12+Simulador!$B$15) -> 238.52276
A13: =IF(ROW()-2<=Simulador!$B$13,ROW()-2,"") | B13: =IF($A13="","",EDATE(Simulador!$B$10,$A13)) | C13: =IF($A13="","",IF($A13=1,Simulador!$B$11,$F12)) | D13: =IF($A13="","",$C13*Simulador!$B$18) | E13: =IF($A13="","",MIN(Simulador!$B$19-$D13,$C13)) | F13: =IF($A13="","",MAX(0,$C13-$E13)) | G13: =IF($A13="","",$D13+$E13+Simulador!$B$15)
A14: =IF(ROW()-2<=Simulador!$B$13,ROW()-2,"") | B14: =IF($A14="","",EDATE(Simulador!$B$10,$A14)) | C14: =IF($A14="","",IF($A14=1,Simulador!$B$11,$F13)) | D14: =IF($A14="","",$C14*Simulador!$B$18) | E14: =IF($A14="","",MIN(Simulador!$B$19-$D14,$C14)) | F14: =IF($A14="","",MAX(0,$C14-$E14)) | G14: =IF($A14="","",$D14+$E14+Simulador!$B$15)
... A362: =IF(ROW()-2<=Simulador!$B$13,ROW()-2,"") | B362: =IF($A362="","",EDATE(Simulador!$B$10,$A362)) | C362: =IF($A362="","",IF($A362=1,Simulador!$B$11,$F361)) | D362: =IF($A362="","",$C362*Simulador!$B$18) | E362: =IF($A362="","",MIN(Simulador!$B$19-$D362,$C362)) | F362: =IF($A362="","",MAX(0,$C362-$E362)) | G362: =IF($A362="","",$D362+$E362+Simulador!$B$15)
